LICENSE
setup.py
ptgcalls_wrapper/__init__.py
ptgcalls_wrapper/controllers.py
ptgcalls_wrapper/converters.py
ptgcalls_wrapper/exceptions.py
ptgcalls_wrapper/streamers.py
ptgcalls_wrapper/wrapper_base.py
ptgcalls_wrapper/wrappers.py
ptgcalls_wrapper.egg-info/PKG-INFO
ptgcalls_wrapper.egg-info/SOURCES.txt
ptgcalls_wrapper.egg-info/dependency_links.txt
ptgcalls_wrapper.egg-info/requires.txt
ptgcalls_wrapper.egg-info/top_level.txt
ptgcalls_wrapper/utils/__init__.py
ptgcalls_wrapper/utils/cmd.py
ptgcalls_wrapper/utils/queues.py
ptgcalls_wrapper/utils/re.py