Metadata-Version: 1.1
Name: ptgcalls-wrapper
Version: 1.1.0
Summary: A library to use the PyTgCalls easier.
Home-page: UNKNOWN
Author: Shohih Abdul
Author-email: shohih242@gmail.com
License: UNKNOWN
Platform: UNKNOWN
Classifier: Programming Language :: Python :: 3
Classifier: License :: OSI Approved :: MIT License
Classifier: Operating System :: OS Independent
